Metadata-Version: 2.4
Name: swxsoc
Version: 0.2.1
Summary: A Python package to support the SWxSOC instrument packages.
Author-email: Steven Christe <steven.d.christe@nasa.gov>, Damian Barrous Dumme <damianbarrous@gmail.com>, Andrew Robbertz <a.robbertz@gmail.com>
License: see licenses/LICENSE.md
Project-URL: Homepage, https://github.com/swxsoc/swxsoc
Project-URL: Documentation, https://swxsoc.readthedocs.io/en/latest/
Keywords: swxsoc,nasa mission,space weather
Classifier: Development Status :: 3 - Alpha
Classifier: Natural Language :: English
Classifier: Operating System :: OS Independent
Classifier: Programming Language :: Python
Classifier: Programming Language :: Python :: 3.9
Classifier: Intended Audience :: Science/Research
Classifier: Topic :: Scientific/Engineering
Classifier: Topic :: Scientific/Engineering :: Physics
Requires-Python: >=3.9
License-File: LICENSE.rst
Requires-Dist: sammi-cdf>=0.1.2
Requires-Dist: astropy>=5.3.3
Requires-Dist: numpy>=1.18.0
Requires-Dist: sunpy[all]>=5.0.1
Requires-Dist: spacepy>=0.5.0
Requires-Dist: ndcube>=2.2.0
Requires-Dist: parfive==2.1.0
Requires-Dist: pyyaml>=5.3.1
Requires-Dist: boto3>=1.35.26
Provides-Extra: dev
Requires-Dist: coverage>=5.0.3; extra == "dev"
Requires-Dist: pytest==8.0.0; extra == "dev"
Requires-Dist: pytest-astropy==0.11.0; extra == "dev"
Requires-Dist: pytest-cov==4.1.0; extra == "dev"
Requires-Dist: black==24.8.0; extra == "dev"
Requires-Dist: flake8==7.0.0; extra == "dev"
Requires-Dist: coverage[toml]==7.4.1; extra == "dev"
Requires-Dist: moto[all]==5.0.15; extra == "dev"
Provides-Extra: docs
Requires-Dist: sphinx==7.2.6; extra == "docs"
Requires-Dist: sphinx-automodapi==0.16.0; extra == "docs"
Requires-Dist: sphinx-copybutton==0.5.2; extra == "docs"
Provides-Extra: test
Requires-Dist: pytest==8.0.0; extra == "test"
Requires-Dist: pytest-astropy==0.11.0; extra == "test"
Requires-Dist: pytest-cov==4.1.0; extra == "test"
Requires-Dist: coverage[toml]==7.4.1; extra == "test"
Requires-Dist: moto[all]==5.0.15; extra == "test"
Provides-Extra: style
Requires-Dist: black==24.8.0; extra == "style"
Requires-Dist: flake8==7.0.0; extra == "style"
Requires-Dist: rstcheck==6.2.0; extra == "style"
Dynamic: license-file
